#######################################################################################################################################
<poster>TNPB</poster>
<fanart>http://1hdwallpapers.com/wallpapers/gr_canyon_thunderstorm.jpg</fanart>
#######################################################################################################################################
<info>
<message>[COLOR red]Just Great Documentaries found here links with multiple episodes are listed in order[/COLOR]</message>
<thumbnail>http://s20.postimg.org/jvq2l8xel/TNPB.png</thumbnail>
</info>
#######################################################################################################################################

<item>
<title></title>
<link>
<sublink></sublink>
<sublink></sublink>
<sublink></sublink>
</link>
<thumbnail></thumbnail>
</item>

<item>
<title></title>
<link>
<sublink></sublink>
<sublink></sublink>
<sublink></sublink>
</link>
<thumbnail></thumbnail>
</item>

<item>
<title></title>
<link>
<sublink></sublink>
<sublink></sublink>
<sublink></sublink>
</link>
<thumbnail></thumbnail>
</item>

<item>
<title></title>
<link>
<sublink></sublink>
<sublink></sublink>
<sublink></sublink>
</link>
<thumbnail></thumbnail>
</item>

<item>
<title></title>
<link>
<sublink></sublink>
<sublink></sublink>
<sublink></sublink>
</link>
<thumbnail></thumbnail>
</item>

<item>
<title>20 Feet from Stardom (2013) (720p)</title>
<link>
<sublink>http://www.firedrive.com/file/EAF66BBA81C864FC</sublink>
<sublink>http://billionuploads.com/the9pav6myil</sublink>
<sublink>http://180upload.com/nxskewytvfl9</sublink>
</link>
<thumbnail>http://image.tmdb.org/t/p/w185/aFQHlH23U9gHhvNn7rr38hFBYce.jpg</thumbnail>
</item>

<item>
<title>Apocalypse: The Second World War (2009) (6 Episodes)</title>
<link>
<sublink>http://www.putlocker.com/file/870BF29CD6839B64</sublink>
<sublink>http://www.putlocker.com/file/1485F8E820B271FA</sublink>
<sublink>http://www.putlocker.com/file/D6806A2DF0B7E653</sublink>
<sublink>http://www.putlocker.com/file/F89F997246DF460C</sublink>
<sublink>http://www.putlocker.com/file/4CBFE3EB97BAE0B6</sublink>
<sublink>http://www.putlocker.com/file/7D621A7D8B4BD19A</sublink>
</link>
<thumbnail>http://www.warhistoryonline.com/wp-content/uploads/2012/10/apocalypse_ii_world_war.jpg</thumbnail>
</item>

<item>
<title>We Steal Secrets: The Story of WikiLeaks (2013)</title>
<link>
<sublink>http://hugefiles.net/5s1k8l7mebwl</sublink>
<sublink>http://megarelease.org/2tpimspqnwha</sublink>
<sublink>http://megarelease.org/2tpimspqnwha</sublink>
</link>
<thumbnail>http://ia.media-imdb.com/images/M/MV5BNTg3MjUyNjkzNl5BMl5BanBnXkFtZTcwMTQzNDgyOQ@@._V1_SX214_.jpg</thumbnail>
</item>

<item>
<title>The Story of AC/DC: Dirty Deeds (2013)</title>
<link>http://www.nowvideo.sx/video/16dd105cd3735</link>
<thumbnail>http://www.mooviemaniac.net/index_htm_files/24676.jpg</thumbnail>
</item>

<item>
<title>Mike Tyson: Undisputed Truth (2013)</title>
<link>http://www.nowvideo.sx/video/7626c74a2139b</link>
<thumbnail>http://image.tmdb.org/t/p/w185/kzyBUpStHNylUOd6VHDFnCgUmPM.jpg</thumbnail>
</item>

<item>
<title>The Class of 92</title>
<link>
<sublink>http://billionuploads.com/zpbs1zuy46r8</sublink>
<sublink>http://movreel.com/6m2l91jv995j</sublink>
<sublink>http://180upload.com/0aaenrfyqrxw</sublink>
</link>
<thumbnail>http://image.tmdb.org/t/p/w185/oC7wDzwfanauYRBsy2KZXSJ9bbg.jpg</thumbnail>
</item>

<item>
<title>Super Tornado</title>
<link>http://www.putlocker.com/file/618ECEAC10E79537</link>
<thumbnail>https://encrypted-tbn2.gstatic.com/images?q=tbn:ANd9GcSw8XojPNJJGHa_aLReUVVITW0Nqok0s9cCoUoPQa7O0RFH1rUV</thumbnail>
</item>

<item>
<title>Tigers Fighting Back</title>
<link>http://www.youtube.com/watch?v=Ap7SmV-bHns</link>
<thumbnail>http://i43.tower.com/images/mm111303105/animal-nation-tigers-fighting-back-dvd-cover-art.jpg</thumbnail>
</item>

<item>
<title>Naughty by Nature</title>
<link>http://www.youtube.com/watch?v=mqM0etXJ6HQ</link>
<thumbnail>http://cdn.tdfimg.com/wp-content/uploads/2013/06/naughty-nature.jpg</thumbnail>
</item>

<item>
<title>The Science of Survival</title>
<link>http://www.youtube.com/watch?v=qVmusHZtQms</link>
<thumbnail>http://i43.tower.com/images/mm117043994/mutations-science-survival-dvd-cover-art.jpg</thumbnail>
</item>

<item>
<title>The Living Planet (12 Episodes)</title>
<link>
<sublink>http://www.youtube.com/watch?v=Ap54bVoN0gc</sublink>
<sublink>http://www.youtube.com/watch?v=A9SivjWXf94</sublink>
<sublink>http://www.youtube.com/watch?v=DE7hNdkNmsI</sublink>
<sublink>http://www.youtube.com/watch?v=bQ7jleKfcIg</sublink>
<sublink>http://www.youtube.com/watch?v=kZUEm-hOuVI</sublink>
<sublink>http://www.youtube.com/watch?v=olELJyQicvk</sublink>
<sublink>http://www.youtube.com/watch?v=gAUsvm_jcJU</sublink>
<sublink>http://www.youtube.com/watch?v=TlhnjTZ3MOM</sublink>
<sublink>http://www.youtube.com/watch?v=GF5NKV4K-T0</sublink>
<sublink>http://www.youtube.com/watch?v=kSBhTgQwTGM</sublink>
<sublink>http://www.youtube.com/watch?v=d7WtduFycDY</sublink>
<sublink>http://www.youtube.com/watch?v=aZIj0QZTfiI</sublink>
</link>
<thumbnail>http://ia.media-imdb.com/images/M/MV5BMTMwNTMyOTY4OF5BMl5BanBnXkFtZTcwNDI0NzgxMQ@@._V1_SY317_CR8,0,214,317_.jpg</thumbnail>
</item>

<item>
<title>The Last Lioness</title>
<link>http://www.youtube.com/watch?v=WG_-FU3NNgw</link>
<thumbnail>http://2.bp.blogspot.com/_A0nlWTOsGTY/TGVcgq0I8BI/AAAAAAAAC8w/GzBxpT1g2HQ/s1600/Last+Lioness.jpg</thumbnail>
</item>

<item>
<title>Supervolcano</title>
<link>http://www.youtube.com/watch?v=4AjQvOWUJ2o</link>
<thumbnail>http://upload.wikimedia.org/wikipedia/en/e/e0/Supervolcano.jpg</thumbnail>
</item>

<item>
<title>David Attenborough's Life (10 Episodes)</title>
<link>
<sublink>http://clicktoview.org/ep7syn0r7jm7</sublink>
<sublink>http://clicktoview.org/93k2udg55nof</sublink>
<sublink>http://clicktoview.org/8kjp4hdarxjt</sublink>
<sublink>http://clicktoview.org/wvbporasm5oy</sublink>
<sublink>http://clicktoview.org/ksgcz8ckb44u</sublink>
<sublink>http://clicktoview.org/ooqrr559pnw6</sublink>
<sublink>http://clicktoview.org/7skecn4xvyf8</sublink>
<sublink>http://clicktoview.org/agf0latqkwsa</sublink>
<sublink>http://clicktoview.org/wh3rcmfmvcao</sublink>
<sublink>http://clicktoview.org/xpdxizxxkksv</sublink>
</link>
<thumbnail>http://ia.media-imdb.com/images/M/MV5BMzc0NzY3MjA0Nl5BMl5BanBnXkFtZTcwNTE3NzQyMw@@._V1_SY317_CR8,0,214,317_.jpg</thumbnail>
</item>

<item>
<title>David Attenborough's The Blue Planet (8 Episodes)</title>
<link>
<sublink>http://gorillavid.in/h0n6ul1n10l8</sublink>
<sublink>http://gorillavid.in/bt8cahi93f6s</sublink>
<sublink>http://gorillavid.in/cdm41rswrecb</sublink>
<sublink>http://gorillavid.in/w6ygwwuv9az5</sublink>
<sublink>http://gorillavid.in/zlmzcwgtl3ly</sublink>
<sublink>http://gorillavid.in/6gtppxaa5t5r</sublink>
<sublink>http://gorillavid.in/5avq4sycrnlx</sublink>
<sublink>http://gorillavid.in/go3rhtvykban</sublink>
</link>
<thumbnail>http://upload.wikimedia.org/wikipedia/en/c/ca/Blueplanet.jpg</thumbnail>
</item>

<item>
<title>David Attenborough's Planet Earth (11 Episodes)</title>
<link>
<sublink>http://movreel.com/36o1mg8qf1fd</sublink>
<sublink>http://movreel.com/taxrdik34l6t</sublink>
<sublink>http://movreel.com/751symmgaynz</sublink>
<sublink>http://movreel.com/fuowio5vxnjy</sublink>
<sublink>http://movreel.com/hehyrek50zjn</sublink>
<sublink>http://movreel.com/qnyu9ax93av2</sublink>
<sublink>http://movreel.com/a1bfg13vieqj</sublink>
<sublink>http://movreel.com/uqqcwymjjg47</sublink>
<sublink>http://movreel.com/01h0ch6p4p5i</sublink>
<sublink>http://movreel.com/uahqeoqkjg5g</sublink>
<sublink>http://movreel.com/62v1pv2hge5n</sublink>
</link>
<thumbnail>http://ia.media-imdb.com/images/M/MV5BNzA0NTQxNzQ3Ml5BMl5BanBnXkFtZTYwMjA1ODU3._V1_SY317_CR6,0,214,317_.jpg</thumbnail>
</item>

<item>
<title>Disney Natures Earth</title>
<link>http://veehd.com/video/2421565_Planet-Earth-HD-2006</link>
<thumbnail>http://ia.media-imdb.com/images/M/MV5BMTUwMzU5NDk3NF5BMl5BanBnXkFtZTcwOTM4MDUwMg@@._V1_SY317_CR0,0,214,317_.jpg</thumbnail>
</item>

<item>
<title>The Great Rift: Africa's Wild Heart</title>
<link>
<sublink>http://www.dailymotion.com/video/xl8jdf_bbc-great-rift-africa-s-wild-heart-1of3-fire-pdtv-xvid-ac3_tech</sublink>
<sublink>http://www.dailymotion.com/video/xl8j5e_bbc-great-rift-africa-s-wild-heart-2of3-water-pdtv-xvid-ac3_tech</sublink>
<sublink>http://www.dailymotion.com/video/xl8ixa_bbc-great-rift-africa-s-wild-heart-3of3-grass-pdtv-xvid-ac3_tech</sublink>
</link>
<thumbnail>http://upload.wikimedia.org/wikipedia/en/5/59/Great_rift_dvd.jpg</thumbnail>
</item>

<item>
<title></title>
<link></link>
<thumbnail></thumbnail>
</item>

