#######################################################################################################################################
<poster>TNPB</poster>
<fanart>http://s20.postimg.org/5c60zrxjx/DOCS_MONTAGE.jpg</fanart>
#######################################################################################################################################

<item>
<title>Doc - Defiant Requiem</title>
<link>http://www.firedrive.com/file/FC7D40368C0F6A8E</link>
<thumbnail>http://image.tmdb.org/t/p/w185/1020WvlzvfzEAYGTs6h2rho4ubM.jpg</thumbnail>
</item>
