#######################################################################################################################################
<poster>TNPB</poster>
<fanart>http://thetvdb.com/banners/fanart/original/78287-1.jpg</fanart>
#######################################################################################################################################
<info>
<message>[COLOR red]REPORT dead links to (Twitter) @BigBallzBaby ... ENJOY!![/COLOR]</message>
<thumbnail>http://s20.postimg.org/jvq2l8xel/TNPB.png</thumbnail>
</info>
#######################################################################################################################################

<item>
<title>1x1 If I Were a Carpenter</title>
<link>http://www.putlocker.com/file/8BCD034F32F36EA1</link>
<thumbnail>http://thetvdb.com/banners/_cache/episodes/78287/278978.jpg</thumbnail>
</item>

<item>
<title>1x2 Who Won the War Anyway?</title>
<link>http://www.putlocker.com/file/043987E113C9A531</link>
<thumbnail>http://thetvdb.com/banners/_cache/episodes/78287/278979.jpg</thumbnail>
</item>

<item>
<title>1x3 The Girls They Left Behind</title>
<link>http://www.putlocker.com/file/F724EB4E6E3E2AE4</link>
<thumbnail>http://thetvdb.com/banners/_cache/episodes/78287/278980.jpg</thumbnail>
</item>

<item>
<title>1x4 Suspicion</title>
<link>http://www.putlocker.com/file/E0401889913710E7</link>
<thumbnail>http://thetvdb.com/banners/_cache/episodes/78287/278981.jpg</thumbnail>
</item>

<item>
<title>1x5 Home Thoughts from Abroad</title>
<link>http://www.putlocker.com/file/D1BB9374F1414EB6</link>
<thumbnail>http://thetvdb.com/banners/_cache/episodes/78287/278982.jpg</thumbnail>
</item>

<item>
<title>1x6 The Accused</title>
<link>http://www.putlocker.com/file/66C557B644B9694C</link>
<thumbnail>http://thetvdb.com/banners/_cache/episodes/78287/278983.jpg</thumbnail>
</item>

<item>
<title>1x7 Private Lives</title>
<link>http://www.putlocker.com/file/9C4E8EC2E7FD7ED6</link>
<thumbnail>http://thetvdb.com/banners/_cache/episodes/78287/278984.jpg</thumbnail>
</item>

<item>
<title>1x8 The Fugitive</title>
<link>http://www.putlocker.com/file/6D49F63AF7E4BDBD</link>
<thumbnail>http://thetvdb.com/banners/_cache/episodes/78287/278985.jpg</thumbnail>
</item>

<item>
<title>1x9 The Alien</title>
<link>http://www.putlocker.com/file/0F4B5E0FF0A97D21</link>
<thumbnail>http://thetvdb.com/banners/_cache/episodes/78287/278986.jpg</thumbnail>
</item>

<item>
<title>1x10 Last Rites</title>
<link>http://www.putlocker.com/file/7BF5EB314C4E028B</link>
<thumbnail>http://thetvdb.com/banners/_cache/episodes/78287/278987.jpg</thumbnail>
</item>

<item>
<title>1x11 The Lovers</title>
<link>http://www.putlocker.com/file/CD0927E4FF43FFEA</link>
<thumbnail>http://thetvdb.com/banners/_cache/episodes/78287/278988.jpg</thumbnail>
</item>

<item>
<title>1x12 Love and Other Four Letter Words</title>
<link>http://www.putlocker.com/file/E8415C83AD174523</link>
<thumbnail>http://thetvdb.com/banners/_cache/episodes/78287/278989.jpg</thumbnail>
</item>

<item>
<title>1x13 When the Boat Goes Out</title>
<link>http://www.putlocker.com/file/B22B6CA24B64046F</link>
<thumbnail>http://thetvdb.com/banners/_cache/episodes/78287/278990.jpg</thumbnail>
</item>
