#######################################################################################################################################
<poster>TNPB</poster>
<fanart>http://thetvdb.com/banners/fanart/original/262414-3.jpg</fanart>
#######################################################################################################################################
<info>
<message>[COLOR red]REPORT dead links to (Twitter) @BigBallzBaby ... ENJOY!![/COLOR]</message>
<thumbnail>http://s20.postimg.org/jvq2l8xel/TNPB.png</thumbnail>
</info>
#######################################################################################################################################

<item>
<title>2x1 Gone but Not Forgotten</title>
<link>https://vk.com/video_ext.php?oid=202799911&id=167618602&hash=28dc0ee9bffbbff9</link>
<thumbnail>http://thetvdb.com/banners/graphical/262414-g.jpg</thumbnail>
</item>

<item>
<title>2x2 Shadow of a Doubt</title>
<link>https://vk.com/video_ext.php?oid=202466121&id=168007117&hash=0881c8b3f4160365</link>
<thumbnail>http://thetvdb.com/banners/graphical/262414-g.jpg</thumbnail>
</item>

<item>
<title>2x3 Caleb</title>
<link>https://vk.com/video_ext.php?oid=200376351&id=167902793&hash=e2902a4a856f5984</link>
<thumbnail>http://thetvdb.com/banners/graphical/262414-g.jpg</thumbnail>
</item>

<item>
<title>2x4 Check-Out</title>
<link>https://vk.com/video_ext.php?oid=247865278&id=169238371&hash=b1d43adc85114baa</link>
<thumbnail>http://thetvdb.com/banners/graphical/262414-g.jpg</thumbnail>
</item>

<item>
<title>2x5 The Escape Artist</title>
<link>https://vk.com/video_ext.php?oid=204407749&id=169016957&hash=597dbe3a0f2c0106</link>
<thumbnail>http://thetvdb.com/banners/graphical/262414-g.jpg</thumbnail>
</item>

<item>
<title>2x6 Plunge</title>
<link>https://vk.com/video_ext.php?oid=172663020&id=168125105&hash=08d7753ec7d4e3b0</link>
<thumbnail>http://thetvdb.com/banners/graphical/262414-g.jpg</thumbnail>
</item>

<item>
<title>2x7 Presumed Innocent</title>
<link>https://vk.com/video_ext.php?oid=202895650&id=168283933&hash=01a7d557386978e0</link>
<thumbnail>http://thetvdb.com/banners/graphical/262414-g.jpg</thumbnail>
</item>

<item>
<title>2x8 Meltdown</title>
<link>https://vk.com/video_ext.php?oid=203493689&id=168416042&hash=fa99e6c3bd86bb56</link>
<thumbnail>http://thetvdb.com/banners/graphical/262414-g.jpg</thumbnail>
</item>

<item>
<title>2x9 The Box</title>
<link>https://vk.com/video_ext.php?oid=204404934&id=168411906&hash=0128715570ff88cd</link>
<thumbnail>http://thetvdb.com/banners/graphical/262414-g.jpg</thumbnail>
</item>

<item>
<title>2x10 The Immutable Truth</title>
<link>https://vk.com/video_ext.php?oid=249803843&id=168596186&hash=1076a7a2d6ebd56f</link>
<thumbnail>http://thetvdb.com/banners/graphical/262414-g.jpg</thumbnail>
</item>
