#######################################################################################################################################
<poster>TNPB</poster>
<fanart>http://thetvdb.com/banners/fanart/original/142831-8.jpg</fanart>
#######################################################################################################################################
<info>
<message>[COLOR red]REPORT dead links to (Twitter) @BigBallzBaby ... ENJOY!![/COLOR]</message>
<thumbnail>http://s20.postimg.org/jvq2l8xel/TNPB.png</thumbnail>
</info>
#######################################################################################################################################

<item>
<title>2x1 Welcome Back Big Time</title>
<link>http://movreel.com/7vatl3cnep3x</link>
<thumbnail>http://thetvdb.com/banners/graphical/142831-g3.jpg</thumbnail>
</item>

<item>
<title>2x2 Big Time Fans</title>
<link>http://movreel.com/1tlreyki93t4</link>
<thumbnail>http://thetvdb.com/banners/graphical/142831-g3.jpg</thumbnail>
</item>

<item>
<title>2x3 Big Time Girlfriends</title>
<link>http://movreel.com/fz5iyk8nev19</link>
<thumbnail>http://thetvdb.com/banners/graphical/142831-g3.jpg</thumbnail>
</item>

<item>
<title>2x4 Big Time Live</title>
<link>http://movreel.com/8e8jvc28yocs</link>
<thumbnail>http://thetvdb.com/banners/graphical/142831-g3.jpg</thumbnail>
</item>

<item>
<title>2x5 Big Time Halloween</title>
<link>http://movreel.com/gm0ebr25lsd8</link>
<thumbnail>http://thetvdb.com/banners/graphical/142831-g3.jpg</thumbnail>
</item>

<item>
<title>2x6 Big Time Sneakers</title>
<link>http://movreel.com/g4963epazd1p</link>
<thumbnail>http://thetvdb.com/banners/graphical/142831-g3.jpg</thumbnail>
</item>

<item>
<title>2x7 Big Time Pranks</title>
<link>http://movreel.com/v0d3jpqsvo8h</link>
<thumbnail>http://thetvdb.com/banners/graphical/142831-g3.jpg</thumbnail>
</item>

<item>
<title>2x8&9 Big Time Christmas (1/2)</title>
<link>http://movreel.com/uuycopathjur</link>
<thumbnail>http://thetvdb.com/banners/graphical/142831-g3.jpg</thumbnail>
</item>

<item>
<title>2x10 Big Time Guru</title>
<link>http://movreel.com/x23oqdzmx1lb</link>
<thumbnail>http://thetvdb.com/banners/graphical/142831-g3.jpg</thumbnail>
</item>

<item>
<title>2x11 Big Time Crush</title>
<link>https://vk.com/video_ext.php?oid=200366433&id=165485607&hash=ca0cf1cae2171fb3</link>
<thumbnail>http://thetvdb.com/banners/graphical/142831-g3.jpg</thumbnail>
</item>

<item>
<title>2x12&13 Big Time Beach Party (1/2)</title>
<link>https://vk.com/video_ext.php?oid=200366433&id=165485624&hash=f15bce6606d84335</link>
<thumbnail>http://thetvdb.com/banners/graphical/142831-g3.jpg</thumbnail>
</item>

<item>
<title>2x14 Big Time Songwriters</title>
<link>http://movreel.com/rhtu1wfgb0ta</link>
<thumbnail>http://thetvdb.com/banners/graphical/142831-g3.jpg</thumbnail>
</item>

<item>
<title>2x15 Big Time Reality</title>
<link>https://vk.com/video_ext.php?oid=200366433&id=165485663&hash=ccc628a31d34cddd</link>
<thumbnail>http://thetvdb.com/banners/graphical/142831-g3.jpg</thumbnail>
</item>

<item>
<title>2x16 Big Time Girl Group</title>
<link>https://vk.com/video_ext.php?oid=200367819&id=165511924&hash=f1d3a29edfd9f65e</link>
<thumbnail>http://thetvdb.com/banners/graphical/142831-g3.jpg</thumbnail>
</item>

<item>
<title>2x17 Green Time Rush</title>
<link>https://vk.com/video_ext.php?oid=200367819&id=165511939&hash=cdd683943fbf4783</link>
<thumbnail>http://thetvdb.com/banners/graphical/142831-g3.jpg</thumbnail>
</item>

<item>
<title>2x18 Big Time Moms</title>
<link>https://vk.com/video_ext.php?oid=200367819&id=165511965&hash=2bbe51a35a5f1389</link>
<thumbnail>http://thetvdb.com/banners/graphical/142831-g3.jpg</thumbnail>
</item>

<item>
<title>2x19 Big Time Prom King</title>
<link>https://vk.com/video_ext.php?oid=202560904&id=167240020&hash=18fd4f32a383e951</link>
<thumbnail>http://thetvdb.com/banners/graphical/142831-g3.jpg</thumbnail>
</item>

<item>
<title>2x20 Big Time Break-Up</title>
<link>https://vk.com/video_ext.php?oid=200367819&id=165511984&hash=06ab8adc036c9b47</link>
<thumbnail>http://thetvdb.com/banners/graphical/142831-g3.jpg</thumbnail>
</item>

<item>
<title>2x21 Big Time Single</title>
<link>https://vk.com/video_ext.php?oid=200367819&id=165511997&hash=a627ef65dac346f5</link>
<thumbnail>http://thetvdb.com/banners/graphical/142831-g3.jpg</thumbnail>
</item>

<item>
<title>2x22 Big Time Wedding</title>
<link>https://vk.com/video_ext.php?oid=200367819&id=165512004&hash=a63bfacc6d39b730</link>
<thumbnail>http://thetvdb.com/banners/graphical/142831-g3.jpg</thumbnail>
</item>

<item>
<title>2x23 Big Time Rocker</title>
<link>https://vk.com/video_ext.php?oid=200367819&id=165512015&hash=abe5411c0e8738ee</link>
<thumbnail>http://thetvdb.com/banners/graphical/142831-g3.jpg</thumbnail>
</item>

<item>
<title>2x24 Big Time Strike</title>
<link>https://vk.com/video_ext.php?oid=200367819&id=165512025&hash=c23aad216734a414</link>
<thumbnail>http://thetvdb.com/banners/graphical/142831-g3.jpg</thumbnail>
</item>

<item>
<title>2x25 Big Time Contest</title>
<link>https://vk.com/video_ext.php?oid=200367819&id=165512034&hash=fab5055c745ed617</link>
<thumbnail>http://thetvdb.com/banners/graphical/142831-g3.jpg</thumbnail>
</item>

<item>
<title>2x26 Big Time Superheroes</title>
<link>https://vk.com/video_ext.php?oid=200367819&id=165512048&hash=dc955709ac245429</link>
<thumbnail>http://thetvdb.com/banners/graphical/142831-g3.jpg</thumbnail>
</item>

<item>
<title>2x27 Big Time Secret</title>
<link>https://vk.com/video_ext.php?oid=200367819&id=165512064&hash=182d99e0960616c3</link>
<thumbnail>http://thetvdb.com/banners/graphical/142831-g3.jpg</thumbnail>
</item>

<item>
<title>2x28 Big Time Interview</title>
<link>https://vk.com/video_ext.php?oid=200367819&id=165512072&hash=2d3d563e93bb7ad2</link>
<thumbnail>http://thetvdb.com/banners/graphical/142831-g3.jpg</thumbnail>
</item>
