#######################################################################################################################################
<poster>TNPB</poster>
<fanart>http://cdn-3.cinemaparadiso.co.uk/clp/349540-13380-clp-950.jpg</fanart>
#######################################################################################################################################
<info>
<message>[COLOR red]REPORT dead links to (Twitter) @BigBallzBaby ... ENJOY!![/COLOR]</message>
<thumbnail>http://s20.postimg.org/jvq2l8xel/TNPB.png</thumbnail>
</info>
#######################################################################################################################################

<item>
<title>2x1 Dawn's Ball</title>
<link>http://www.firedrive.com/file/00669E7C2C5083EE</link>
<thumbnail>http://busstop.typepad.com/blog/images/preston3_sm.jpg</thumbnail>
</item>

<item>
<title>2x2 Laura's Mousse</title>
<link>http://www.firedrive.com/file/38A2A9E1DB94EC43</link>
<thumbnail>http://busstop.typepad.com/blog/images/preston3_sm.jpg</thumbnail>
</item>

<item>
<title>2x3 Spock's Leg</title>
<link>http://www.firedrive.com/file/BF667E72D93CC4FE</link>
<thumbnail>http://busstop.typepad.com/blog/images/preston3_sm.jpg</thumbnail>
</item>

<item>
<title>2x4 Polson's Lilo</title>
<link>http://www.firedrive.com/file/0379B3A0D9AC85D1</link>
<thumbnail>http://busstop.typepad.com/blog/images/preston3_sm.jpg</thumbnail>
</item>

<item>
<title>2x5 Diesel's Out of Body Experience</title>
<link>http://www.firedrive.com/file/EAEB563C6E584485</link>
<thumbnail>http://busstop.typepad.com/blog/images/preston3_sm.jpg</thumbnail>
</item>

<item>
<title>2x6 Lloydy's Ark</title>
<link>http://www.firedrive.com/file/0A6C4BFD6A51FC79</link>
<thumbnail>http://busstop.typepad.com/blog/images/preston3_sm.jpg</thumbnail>
</item>
