#######################################################################################################################################
<poster>TNPB</poster>
<fanart>http://thetvdb.com/banners/fanart/original/212961-8.jpg</fanart>
#######################################################################################################################################
<info>
<message>[COLOR red]REPORT dead links to (Twitter) @BigBallzBaby ... ENJOY!![/COLOR]</message>
<thumbnail>http://s20.postimg.org/jvq2l8xel/TNPB.png</thumbnail>
</info>
#######################################################################################################################################

<item>
<title>1x1 Pilot</title>
<link>https://vk.com/video_ext.php?oid=172860651&id=162948214&hash=14046c183c6dbedc</link>
<thumbnail>http://thetvdb.com/banners/graphical/212961-g10.jpg</thumbnail>
</item>

<item>
<title>1x2 Immoral Mathematics</title>
<link>https://vk.com/video_ext.php?oid=172860651&id=162948213&hash=e9c47e516a46e992</link>
<thumbnail>http://thetvdb.com/banners/graphical/212961-g10.jpg</thumbnail>
</item>

<item>
<title>1x3 A New Birth Of Freedom</title>
<link>https://vk.com/video_ext.php?oid=172860651&id=162948210&hash=c77973379b8c9876</link>
<thumbnail>http://thetvdb.com/banners/graphical/212961-g10.jpg</thumbnail>
</item>

<item>
<title>1x4 Jamais Je Ne T'oublierai</title>
<link>https://vk.com/video_ext.php?oid=172860651&id=162948211&hash=c067be62e1f5e726</link>
<thumbnail>http://thetvdb.com/banners/graphical/212961-g10.jpg</thumbnail>
</item>

<item>
<title>1x5 Bread And Circuses</title>
<link>https://vk.com/video_ext.php?oid=172860651&id=162948207&hash=c923abe1d197ae34</link>
<thumbnail>http://thetvdb.com/banners/graphical/212961-g10.jpg</thumbnail>
</item>

<item>
<title>1x6 Pride, Pomp, And Circumstance</title>
<link>https://vk.com/video_ext.php?oid=172860651&id=162948205&hash=2d9f4057b1cbb8a8</link>
<thumbnail>http://thetvdb.com/banners/graphical/212961-g10.jpg</thumbnail>
</item>

<item>
<title>1x7 Revelations</title>
<link>https://vk.com/video_ext.php?oid=172860651&id=162948204&hash=322b38eea27fa1ff</link>
<thumbnail>http://thetvdb.com/banners/graphical/212961-g10.jpg</thumbnail>
</item>

<item>
<title>1x8 Derailed</title>
<link>https://vk.com/video_ext.php?oid=172860651&id=162948203&hash=7157637bff4ad460</link>
<thumbnail>http://thetvdb.com/banners/graphical/212961-g10.jpg</thumbnail>
</item>

<item>
<title>1x9 Timshel</title>
<link>https://vk.com/video_ext.php?oid=172860651&id=162948201&hash=e3fb15ce08389a13</link>
<thumbnail>http://thetvdb.com/banners/graphical/212961-g10.jpg</thumbnail>
</item>

<item>
<title>1x10 God Of Chaos</title>
<link>https://vk.com/video_ext.php?oid=172860651&id=162948200&hash=decd4037884ed808</link>
<thumbnail>http://thetvdb.com/banners/graphical/212961-g10.jpg</thumbnail>
</item>
