#######################################################################################################################################
<poster>TNPB</poster>
<fanart>http://thetvdb.com/banners/fanart/original/80337-30.jpg</fanart>
#######################################################################################################################################
<info>
<message>[COLOR red]REPORT dead links to (Twitter) @BigBallzBaby ... ENJOY!![/COLOR]</message>
<thumbnail>http://s20.postimg.org/jvq2l8xel/TNPB.png</thumbnail>
</info>
#######################################################################################################################################

<item>
<title>3x1 Out of Town</title>
<link></link>
<thumbnail>http://thetvdb.com/banners/_cache/episodes/80337/982661.jpg</thumbnail>
</item>

<item>
<title>3x2 Love Among the Ruins</title>
<link></link>
<thumbnail>http://thetvdb.com/banners/_cache/episodes/80337/1007571.jpg</thumbnail>
</item>

<item>
<title>3x3 My Old Kentucky Home</title>
<link></link>
<thumbnail>http://thetvdb.com/banners/_cache/episodes/80337/1007581.jpg</thumbnail>
</item>

<item>
<title>3x4 The Arrangements</title>
<link></link>
<thumbnail>http://thetvdb.com/banners/_cache/episodes/80337/1007601.jpg</thumbnail>
</item>

<item>
<title>3x5 The Fog</title>
<link></link>
<thumbnail>http://thetvdb.com/banners/_cache/episodes/80337/1007621.jpg</thumbnail>
</item>

<item>
<title>3x6 Guy Walks Into an Advertising Agency</title>
<link></link>
<thumbnail>http://thetvdb.com/banners/_cache/episodes/80337/1007641.jpg</thumbnail>
</item>

<item>
<title>3x7 Seven Twenty Three</title>
<link></link>
<thumbnail>http://thetvdb.com/banners/_cache/episodes/80337/1007661.jpg</thumbnail>
</item>

<item>
<title>3x8 Souvenir</title>
<link></link>
<thumbnail>http://thetvdb.com/banners/_cache/episodes/80337/1007671.jpg</thumbnail>
</item>

<item>
<title>3x9 Wee Small Hours</title>
<link></link>
<thumbnail>http://thetvdb.com/banners/_cache/episodes/80337/1007681.jpg</thumbnail>
</item>

<item>
<title>3x10 The Color Blue</title>
<link></link>
<thumbnail>http://thetvdb.com/banners/_cache/episodes/80337/1007691.jpg</thumbnail>
</item>

<item>
<title>3x11 The Gypsy and the Hobo</title>
<link></link>
<thumbnail>http://thetvdb.com/banners/_cache/episodes/80337/1007701.jpg</thumbnail>
</item>

<item>
<title>3x12 The Grown-Ups</title>
<link></link>
<thumbnail>http://thetvdb.com/banners/_cache/episodes/80337/1007711.jpg</thumbnail>
</item>

<item>
<title>3x13 Shut the Door, Have a Seat</title>
<link></link>
<thumbnail>http://thetvdb.com/banners/_cache/episodes/80337/1007721.jpg</thumbnail>
</item>
