#######################################################################################################################################
<poster>TNPB</poster>
<fanart>http://thetvdb.com/banners/fanart/original/80337-30.jpg</fanart>
#######################################################################################################################################
<info>
<message>[COLOR red]REPORT dead links to (Twitter) @BigBallzBaby ... ENJOY!![/COLOR]</message>
<thumbnail>http://s20.postimg.org/jvq2l8xel/TNPB.png</thumbnail>
</info>
#######################################################################################################################################

<item>
<title>6x1 The Doorway (1)</title>
<link>https://vk.com/video_ext.php?oid=-52758866&id=164879688&hash=0434522c38b8624d</link>
<thumbnail>http://thetvdb.com/banners/_cache/episodes/80337/4468357.jpg</thumbnail>
</item>

<item>
<title>6x2 The Doorway (2)</title>
<link>https://vk.com/video_ext.php?oid=-48047237&id=164808046&hash=da0ae76a20e363e6</link>
<thumbnail>http://thetvdb.com/banners/_cache/episodes/80337/4468357.jpg</thumbnail>
</item>

<item>
<title>6x3 The Collaborators</title>
<link>https://vk.com/video_ext.php?oid=-47696045&id=165448908&hash=cebec3f8a89caf9d</link>
<thumbnail>http://thetvdb.com/banners/_cache/episodes/80337/4531386.jpg</thumbnail>
</item>

<item>
<title>6x4 To Have and to Hold</title>
<link>https://vk.com/video_ext.php?oid=-52758866&id=164862612&hash=6abddcf7253d62eb</link>
<thumbnail>http://thetvdb.com/banners/_cache/episodes/80337/4531387.jpg</thumbnail>
</item>

<item>
<title>6x5 The Flood</title>
<link>http://www.nowvideo.sx/video/8ba024e1494cf</link>
<thumbnail>http://thetvdb.com/banners/_cache/episodes/80337/4531388.jpg</thumbnail>
</item>

<item>
<title>6x6 For Immediate Release</title>
<link>http://www.nowvideo.sx/video/97cfa72e57c62</link>
<thumbnail>http://thetvdb.com/banners/_cache/episodes/80337/4547932.jpg</thumbnail>
</item>

<item>
<title>6x7 Man With a Plan</title>
<link>https://vk.com/video_ext.php?oid=-57559381&id=165942454&hash=edabefbdf3ddf189</link>
<thumbnail>http://thetvdb.com/banners/_cache/episodes/80337/4547935.jpg</thumbnail>
</item>

<item>
<title>6x8 The Crash</title>
<link>http://www.nowvideo.sx/video/5a502ec8adddb</link>
<thumbnail>http://thetvdb.com/banners/_cache/episodes/80337/4550925.jpg</thumbnail>
</item>

<item>
<title>6x9 The Better Half</title>
<link>https://vk.com/video_ext.php?oid=-53756615&id=165368116&hash=e857d08890b6201f</link>
<thumbnail>http://thetvdb.com/banners/_cache/episodes/80337/4562482.jpg</thumbnail>
</item>

<item>
<title>6x10 A Tale of Two Cities</title>
<link>https://vk.com/video_ext.php?oid=-53756615&id=165417655&hash=39acb7ea88676039</link>
<thumbnail>http://thetvdb.com/banners/_cache/episodes/80337/4562483.jpg</thumbnail>
</item>

<item>
<title>6x11 Favors</title>
<link>https://vk.com/video_ext.php?oid=-53756615&id=165470402&hash=903e1aac2fa8e969</link>
<thumbnail>http://thetvdb.com/banners/_cache/episodes/80337/4573576.jpg</thumbnail>
</item>

<item>
<title>6x12 The Quality of Mercy</title>
<link>https://vk.com/video_ext.php?oid=-53756615&id=165524983&hash=a4ed301afd53a6e6</link>
<thumbnail>http://thetvdb.com/banners/_cache/episodes/80337/4573577.jpg</thumbnail>
</item>

<item>
<title>6x13 In Care Of</title>
<link>https://vk.com/video_ext.php?oid=-53756615&id=165568356&hash=589f3f098dc2b02f</link>
<thumbnail>http://thetvdb.com/banners/_cache/episodes/80337/4576951.jpg</thumbnail>
</item>
