#######################################################################################################################################
<poster>TNPB</poster>
<fanart>http://thetvdb.com/banners/fanart/original/72492-5.jpg</fanart>
#######################################################################################################################################
<info>
<message>[COLOR red]REPORT dead links to (Twitter) @BigBallzBaby ... ENJOY!![/COLOR]</message>
<thumbnail>http://s20.postimg.org/jvq2l8xel/TNPB.png</thumbnail>
</info>
#######################################################################################################################################

<item>
<title>2x1 Destination: Royston Vasey</title>
<link>https://vk.com/video_ext.php?oid=-43908592&id=163563014&hash=94779ed09d187d75</link>
<thumbnail>http://thetvdb.com/banners/_cache/episodes/72492/87703.jpg</thumbnail>
</item>

<item>
<title>2x2 Lust for Royston Vasey</title>
<link>https://vk.com/video_ext.php?oid=-43908592&id=163563024&hash=6097c9127b71b41a</link>
<thumbnail>http://thetvdb.com/banners/_cache/episodes/72492/87704.jpg</thumbnail>
</item>

<item>
<title>2x3 A Plague on Royston Vasey</title>
<link>https://vk.com/video_ext.php?oid=-43908592&id=163563035&hash=0caf1edcdaadc9cb</link>
<thumbnail>http://thetvdb.com/banners/_cache/episodes/72492/87705.jpg</thumbnail>
</item>

<item>
<title>2x4 Death in Royston Vasey</title>
<link>https://vk.com/video_ext.php?oid=-43908592&id=163563044&hash=bb039ce3942a6b54</link>
<thumbnail>http://thetvdb.com/banners/_cache/episodes/72492/87706.jpg</thumbnail>
</item>

<item>
<title>2x5 Anarchy in Royston Vasey</title>
<link>https://vk.com/video_ext.php?oid=-43908592&id=163563209&hash=138317113e79c510</link>
<thumbnail>http://thetvdb.com/banners/_cache/episodes/72492/87707.jpg</thumbnail>
</item>

<item>
<title>2x6 Royston Vasey and the Monster from Hell</title>
<link>https://vk.com/video_ext.php?oid=-43908592&id=163563212&hash=0d602c4868990cde</link>
<thumbnail>http://thetvdb.com/banners/_cache/episodes/72492/87708.jpg</thumbnail>
</item>