#######################################################################################################################################
<poster>TNPB</poster>
<fanart>http://thetvdb.com/banners/fanart/original/82840-3.jpg</fanart>
#######################################################################################################################################
<info>
<message>[COLOR red]REPORT dead links to (Twitter) @BigBallzBaby ... ENJOY!![/COLOR]</message>
<thumbnail>http://s20.postimg.org/jvq2l8xel/TNPB.png</thumbnail>
</info>
#######################################################################################################################################

<item>
<title>1x1 Life, Darwin & Everything</title>
<link>https://vk.com/video_ext.php?oid=-17757141&id=159574547&hash=8d74b68549546e2b</link>
<thumbnail>http://thetvdb.com/banners/graphical/82840-g2.jpg</thumbnail>
</item>

<item>
<title>1x2 The Fifth Ape</title>
<link>https://vk.com/video_ext.php?oid=-17757141&id=159574541&hash=467070f31ddf6bb3</link>
<thumbnail>http://thetvdb.com/banners/graphical/82840-g2.jpg</thumbnail>
</item>

<item>
<title>1x3 God Strikes Back</title>
<link>https://vk.com/video_ext.php?oid=-17757141&id=159574532&hash=d1bd55892bc3d402</link>
<thumbnail>http://thetvdb.com/banners/graphical/82840-g2.jpg</thumbnail>
</item>

